rayman/__init__.py
rayman-0.0.1.dist-info/METADATA
rayman-0.0.1.dist-info/WHEEL
rayman-0.0.1.dist-info/licenses/LICENSE
rayman-0.0.1.dist-info/RECORD
